dado/__init__.py
dado/dado.py
dado/py.typed
dado-0.1.4.dist-info/LICENSE
dado-0.1.4.dist-info/METADATA
dado-0.1.4.dist-info/WHEEL
dado-0.1.4.dist-info/top_level.txt
dado-0.1.4.dist-info/RECORD
